{
  "tc_id": "TC-PRESUPUESTO-01",
  "tc_name": "Presupuesto duro — precio_max explicito",
  "group": "G5",
  "type": "NEW",
  "status": "PASS",
  "pass_count": 1,
  "total_runs": 1,
  "ts": "2026-07-01 17:08",
  "ts_file": "20260701_1708",
  "runs": [
    {
      "run_id": 1,
      "pass": true,
      "turns": [
        {
          "turn": 1,
          "user": "quiero rosas maximo 30 euros",
          "agent": "Claro, mira, tenemos estas opciones de rosas por menos de 30 euros:\n\n*   Ramo de Rosas Amarillo — M (12 flores, 25€)\n*   Ramo de Rosas Blanco — M (12 flores, 25€)\n*   Ramo de Rosas Rosa — M (6 flores, 15€)\n\n¿Alguna te gusta?",
          "playbook": "unknown",
          "params": {
            "intencion_inicial": "quiero rosas maximo 30 euros",
            "producto": "rosas",
            "ocasion_detectada": "No indicada",
            "precio_max": 30,
            "grupo_intent": "G5"
          },
          "checks": {
            "pass": true,
            "details": [
              "OK: Agente dijo [rosa]"
            ]
          },
          "trace": {
            "currentPlaybook": "unknown",
            "matchType": "PLAYBOOK",
            "confidence": 1,
            "diagnosticInfo_keys": [
              "Session Id",
              "Response Id"
            ]
          }
        }
      ]
    }
  ],
  "metadata": {
    "orquestador": "v65",
    "compra": "v39",
    "checkout": "v33",
    "registro": "v7 (Task)",
    "script": "v23"
  }
}