{
  "tc_id": "TC-INSULTO-01",
  "tc_name": "Lexico abusivo — agente mantiene tono profesional, no repite",
  "group": "COMPRA-ZG",
  "type": "EDGE",
  "status": "PASS",
  "pass_count": 1,
  "total_runs": 1,
  "ts": "2026-05-29 08:18",
  "ts_file": "20260529_0818",
  "runs": [
    {
      "run_id": 1,
      "pass": true,
      "turns": [
        {
          "turn": 1,
          "user": "esto es una mierda, que porqueria",
          "agent": "Lamento mucho que te sientas así. Te pongo en contacto con un compañero para que te ayude. Hola, soy Alicia. He recibido tu solicitud. Me pondré en contacto enseguida. ¡Hasta pronto!",
          "playbook": "unknown",
          "params": {
            "modo_tono": "estandar",
            "razon_handoff": "cliente_solicita_humano"
          },
          "checks": {
            "pass": true,
            "details": [
              "OK: Agente dijo [lament]"
            ]
          },
          "trace": {
            "currentPlaybook": "unknown",
            "matchType": "PLAYBOOK",
            "confidence": 1,
            "diagnosticInfo_keys": [
              "Session Id",
              "Response Id"
            ]
          }
        }
      ]
    }
  ],
  "metadata": {
    "orquestador": "v65",
    "compra": "v39",
    "checkout": "v33",
    "registro": "v7 (Task)",
    "script": "v23"
  }
}